vhdeps/__init__.py
vhdeps/__main__.py
vhdeps/target.py
vhdeps/version.py
vhdeps/vhdl.py
vhdeps/targets/__init__.py
vhdeps/targets/dump.py
vhdeps/targets/ghdl.py
vhdeps/targets/shared.py
vhdeps/targets/vsim.py
vhdeps-0.4.2.dist-info/LICENSE
vhdeps-0.4.2.dist-info/METADATA
vhdeps-0.4.2.dist-info/WHEEL
vhdeps-0.4.2.dist-info/entry_points.txt
vhdeps-0.4.2.dist-info/top_level.txt
vhdeps-0.4.2.dist-info/RECORD
