Metadata-Version: 2.1
Name: vhdeps
Version: 0.4.2
Summary: VHDL dependency analyzer and simulation driver.
Home-page: https://github.com/abs-tudelft/vhdeps
Author: Jeroen van Straten
Author-email: j.vanstraten-1@tudelft.nl
License: Apache
Project-URL: Source, https://github.com/abs-tudelft/vhdeps
Keywords: vhdl dependency analyzer simulation
Platform: UNKNOWN
Classifier: Development Status :: 4 - Beta
Classifier: Intended Audience :: Developers
Classifier: Topic :: Software Development :: Build Tools
Classifier: License :: OSI Approved :: Apache Software License
Classifier: Programming Language :: Python :: 3
Requires-Python: >=3
Requires-Dist: lcov-cobertura
Requires-Dist: plumbum
